bapao/__init__.py
bapao/cli.py
bapao/commands/__init__.py
bapao/commands/cleanup.py
bapao/commands/forge.py
bapao/commands/init.py
bapao/commands/list_profiles.py
bapao/commands/vault.py
bapao/commands/verify.py
bapao/commands/wire.py
bapao/core/__init__.py
bapao/core/config.py
bapao/core/git_ssh.py
bapao/core/keys.py
bapao/core/passkey.py
bapao/core/quantum_crypto.py
bapao-0.0.8.dist-info/licenses/LICENSE
bapao-0.0.8.dist-info/METADATA
bapao-0.0.8.dist-info/WHEEL
bapao-0.0.8.dist-info/entry_points.txt
bapao-0.0.8.dist-info/top_level.txt
bapao-0.0.8.dist-info/RECORD
