Metadata-Version: 2.4
Name: bapao
Version: 0.0.8
Summary: Developer Environment Sync Engine - Make your entire development environment portable
Home-page: https://gitlab.com/bapao/bapao-sync
Author: BAPAO Team
Author-email: KankerBapao <4duxjx7x9jr7covy0sv7@kubehub.eu>
Maintainer-email: KankerBapao <4duxjx7x9jr7covy0sv7@kubehub.eu>
License: Proprietary
Project-URL: Homepage, https://example.com
Keywords: development,environment,sync,git,ssh,gpg,devtools
Classifier: Development Status :: 3 - Alpha
Classifier: Intended Audience :: Developers
Classifier: License :: Other/Proprietary License
Classifier: Operating System :: OS Independent
Classifier: Operating System :: POSIX :: Linux
Classifier: Operating System :: MacOS
Classifier: Operating System :: Microsoft :: Windows
Classifier: Programming Language :: Python :: 3
Classifier: Programming Language :: Python :: 3.8
Classifier: Programming Language :: Python :: 3.9
Classifier: Programming Language :: Python :: 3.10
Classifier: Programming Language :: Python :: 3.11
Classifier: Programming Language :: Python :: 3.12
Classifier: Topic :: Software Development :: Libraries :: Python Modules
Classifier: Topic :: System :: Systems Administration
Classifier: Topic :: Utilities
Requires-Python: >=3.8
License-File: LICENSE
Requires-Dist: click>=8.0.0
Requires-Dist: pyyaml>=6.0
Requires-Dist: cryptography>=3.4.0
Requires-Dist: rich>=10.0.0
Requires-Dist: pathlib>=1.0.0
Requires-Dist: bcrypt>=4.0.0
Provides-Extra: dev
Requires-Dist: pytest>=7.0.0; extra == "dev"
Requires-Dist: pytest-cov>=4.0.0; extra == "dev"
Requires-Dist: black>=22.0.0; extra == "dev"
Requires-Dist: isort>=5.10.0; extra == "dev"
Requires-Dist: flake8>=4.0.0; extra == "dev"
Requires-Dist: mypy>=0.950; extra == "dev"
Dynamic: author
Dynamic: home-page
Dynamic: license-file
Dynamic: requires-python
